azureml/__init__.py
azureml/contrib/__init__.py
azureml/contrib/services/__init__.py
azureml/contrib/services/aml_request.py
azureml/contrib/services/aml_response.py
azureml_contrib_services-1.60.0.dist-info/licenses/LICENSE.txt
azureml_contrib_services-1.60.0.dist-info/METADATA
azureml_contrib_services-1.60.0.dist-info/WHEEL
azureml_contrib_services-1.60.0.dist-info/top_level.txt
azureml_contrib_services-1.60.0.dist-info/RECORD
